cmsplugin_carousel_ai/__init__.py
cmsplugin_carousel_ai/cms_plugins.py
cmsplugin_carousel_ai/models.py
cmsplugin_carousel_ai/migrations/0001_initial.py
cmsplugin_carousel_ai/migrations/0002_add_call_to_action_label_for_slides.py
cmsplugin_carousel_ai/migrations/0003_slide_description.py
cmsplugin_carousel_ai/migrations/__init__.py
cmsplugin_carousel_ai/templates/cmsplugin_carousel_ai/carousel.html
cmsplugin_carousel_ai-0.0.3.dist-info/DESCRIPTION.rst
cmsplugin_carousel_ai-0.0.3.dist-info/METADATA
cmsplugin_carousel_ai-0.0.3.dist-info/RECORD
cmsplugin_carousel_ai-0.0.3.dist-info/WHEEL
cmsplugin_carousel_ai-0.0.3.dist-info/metadata.json
cmsplugin_carousel_ai-0.0.3.dist-info/top_level.txt
