Metadata-Version: 2.0
Name: cmsplugin-carousel-ai
Version: 0.0.3
Summary: Image carousel plugin for Django CMS
Home-page: https://github.com/andersinno/cmsplugin-carousel-ai
Author: Anders Innovations
Author-email: info@anders.fi
License: MIT
Platform: UNKNOWN
Requires-Dist: django-cms (<3.4,>=3.2)
Requires-Dist: django-enumfields (>=0.8.2)
Requires-Dist: django-filer (>=1.2.4)
Requires-Dist: easy-thumbnails (>=2.3)
